LICENSE.txt
README.md
setup.py
ULN2003Pi/ULN2003.py
ULN2003Pi/__init__.py
ULN2003Pi.egg-info/PKG-INFO
ULN2003Pi.egg-info/SOURCES.txt
ULN2003Pi.egg-info/dependency_links.txt
ULN2003Pi.egg-info/top_level.txt